torchninja/__init__.py
torchninja/core/__init__.py
torchninja/core/trainer.py
torchninja/core/tune.py
torchninja/core/utils/__init__.py
torchninja/core/utils/logger.py
torchninja/core/utils/metrics.py
torchninja/core/utils/utils.py
torchninja/utils/__init__.py
torchninja/utils/loaders.py
torchninja-0.1.3.dist-info/METADATA
torchninja-0.1.3.dist-info/WHEEL
torchninja-0.1.3.dist-info/top_level.txt
torchninja-0.1.3.dist-info/RECORD
