Metadata-Version: 2.1
Name: torchninja
Version: 0.1.3
Summary: Tools for training PyTorch models
Home-page: https://github.com/silvaan/torchninja
Author: Silvan Ferreira
Author-email: silvanfj@gmail.com
Classifier: Development Status :: 3 - Alpha
Classifier: Intended Audience :: Developers
Classifier: License :: OSI Approved :: MIT License
Classifier: Programming Language :: Python :: 3
Classifier: Programming Language :: Python :: 3.6
Classifier: Programming Language :: Python :: 3.7
Classifier: Programming Language :: Python :: 3.8
Classifier: Programming Language :: Python :: 3.9
Requires-Dist: matplotlib
Requires-Dist: numpy
Requires-Dist: torch
Requires-Dist: torchvision
Requires-Dist: tensorboard
Requires-Dist: tqdm
